Hardware/chip_design/flow_artifacts/mac4_base.v
// mac4: a 4-bit multiply-accumulate unit -- one cell of a MAC array.
//   acc <= clear ? 0 : (en ? acc + a*b : acc)
module mac4 (
    input  wire       clk,
    input  wire       rst_n,      // asynchronous reset, active low
    input  wire       clear,      // synchronous clear
    input  wire       en,
    input  wire [3:0] a,
    input  wire [3:0] b,
    output reg  [7:0] acc
);
    wire [7:0] prod = a * b;      // combinational: a 4x4 multiplier

    always @(posedge clk or negedge rst_n) begin
        if (!rst_n)       acc <= 8'd0;
        else if (clear)   acc <= 8'd0;
        else if (en)      acc <= acc + prod;   // combinational adder + mux, then 8 flops
    end
endmodule

Hardware/chip_design/flow_artifacts/tb.v
`timescale 1ns/1ps
module tb;
    reg clk = 0, rst_n = 0, clear = 0, en = 0;
    reg [3:0] a = 0, b = 0;
    wire [7:0] acc;
    reg [7:0] expected = 0;
    integer i, errors = 0;

    mac4 dut (.clk(clk), .rst_n(rst_n), .clear(clear), .en(en), .a(a), .b(b), .acc(acc));
    always #0.5 clk = ~clk;                       // 1 GHz clock: the target we will constrain to

    initial begin
        $dumpfile("waves.vcd"); $dumpvars(0, tb);
        #1.2 rst_n = 1;
        // directed test: 3*5, then 2*7, then clear, then 15*15
        @(negedge clk) en = 1; a = 3;  b = 5;
        @(negedge clk) a = 2;  b = 7;
        @(negedge clk) en = 0; clear = 1;
        @(negedge clk) clear = 0; en = 1; a = 15; b = 15;
        @(negedge clk) en = 0;
        // constrained-random test: 200 cycles against the reference model
        for (i = 0; i < 200; i = i + 1) begin
            @(negedge clk);
            a = $random; b = $random; en = ($random % 4) != 0; clear = ($random % 16) == 0;
        end
        @(negedge clk) $display("random test done: %0d mismatches", errors); $finish;
    end

    // the reference model + scoreboard, checked at every clock edge
    always @(posedge clk or negedge rst_n) begin
        if (!rst_n) expected <= 0;
        else if (clear) expected <= 0;
        else if (en) expected <= expected + a * b;
    end
    always @(negedge clk) if (rst_n && acc !== expected) begin
        errors = errors + 1;
        $display("MISMATCH t=%0t acc=%0d expected=%0d", $time, acc, expected);
    end
endmodule

Hardware/chip_design/flow_artifacts/waves.vcd
$date
	Mon Sep 14 00:57:04 2026
$end
$version
	Icarus Verilog
$end
$timescale
	1ps
$end
$scope module tb $end
$var wire 8 ! acc [7:0] $end
$var reg 4 " a [3:0] $end
$var reg 4 # b [3:0] $end
$var reg 1 $ clear $end
$var reg 1 % clk $end
$var reg 1 & en $end
$var reg 8 ' expected [7:0] $end
$var reg 1 ( rst_n $end
$var integer 32 ) errors [31:0] $end
$var integer 32 * i [31:0] $end
$scope module dut $end
$var wire 4 + a [3:0] $end
$var wire 4 , b [3:0] $end
$var wire 1 $ clear $end
$var wire 1 % clk $end
$var wire 1 & en $end
$var wire 1 ( rst_n $end
$var wire 8 - prod [7:0] $end
$var reg 8 . acc [7:0] $end
$upscope $end
$upscope $end
$enddefinitions $end
$comment Show the parameter values. $end
$dumpall
$end
#0
$dumpvars
b0 .
b0 -
b0 ,
b0 +
bx *
b0 )
0(
b0 '
0&
0%
0$
b0 #
b0 "
b0 !
$end
#500
1%
#1000
0%
#1200
1(
#1500
1%
#2000
b1111 -
b101 #
b101 ,
b11 "
b11 +
1&
0%
#2500
b1111 '
b1111 !
b1111 .
1%
#3000
b1110 -
b111 #
b111 ,
b10 "
b10 +
0%
#3500
b11101 !
b11101 .
b11101 '
1%
#4000
1$
0&
0%
#4500
b0 '
b0 !
b0 .
1%
#5000
b11100001 -
b1111 #
b1111 ,
b1111 "
b1111 +
1&
0$
0%
#5500
b11100001 !
b11100001 .
b11100001 '
1%
#6000
b0 *
0&
0%
#6500
1%
#7000
b100 -
b1 *
1&
b1 #
b1 ,
b100 "
b100 +
0%
#7500
b11100101 !
b11100101 .
b11100101 '
1%
#8000
b10101001 -
b10 *
b1101 #
b1101 ,
b1101 "
b1101 +
0%
#8500
b10001110 '
b10001110 !
b10001110 .
1%
#9000
b1101 -
b11 *
b1 "
b1 +
0%
#9500
b10011011 !
b10011011 .
b10011011 '
1%
#10000
b10011100 -
b100 *
b1100 #
b1100 ,
b1101 "
b1101 +
0%
#10500
b110111 '
b110111 !
b110111 .
1%
#11000
b110010 -
b101 *
b1010 #
b1010 ,
b101 "
b101 +
0%
#11500
b1101001 !
b1101001 .
b1101001 '
1%
#12000
b11110 -
b110 *
b1111 #
b1111 ,
b10 "
b10 +
0%
#12500
b10000111 '
b10000111 !
b10000111 .
1%
#13000
b101000 -
b111 *
0&
b101 #
b101 ,
b1000 "
b1000 +
0%
#13500
1%
#14000
b1000001 -
b1000 *
1&
b1101 "
b1101 +
0%
#14500
b11001000 '
b11001000 !
b11001000 .
1%
#15000
b0 -
b1001 *
b0 #
b0 ,
b0 "
b0 +
0%
#15500
1%
#16000
b10010 -
b1010 *
b11 #
b11 ,
b110 "
b110 +
0%
#16500
b11011010 '
b11011010 !
b11011010 .
1%
#17000
b110111 -
b1011 *
b101 #
b101 ,
b1011 "
b1011 +
0%
#17500
b10001 !
b10001 .
b10001 '
1%
#18000
b11000011 -
b1100 *
b1111 #
b1111 ,
b1101 "
b1101 +
0%
#18500
b11010100 '
b11010100 !
b11010100 .
1%
#19000
b1111000 -
b1101 *
b1100 #
b1100 ,
b1010 "
b1010 +
0%
#19500
b1001100 !
b1001100 .
b1001100 '
1%
#20000
b1000 -
b1110 *
0&
b1000 #
b1000 ,
b1 "
b1 +
0%
#20500
1%
#21000
b1000010 -
b1111 *
1&
b110 #
b110 ,
b1011 "
b1011 +
0%
#21500
b10001110 !
b10001110 .
b10001110 '
1%
#22000
b1111000 -
b10000 *
b1010 #
b1010 ,
b1100 "
b1100 +
0%
#22500
b110 '
b110 !
b110 .
1%
#23000
b1001011 -
b10001 *
b1111 #
b1111 ,
b101 "
b101 +
0%
#23500
b1010001 !
b1010001 .
b1010001 '
1%
#24000
b1000110 -
b10010 *
b101 #
b101 ,
b1110 "
b1110 +
0%
#24500
b10010111 '
b10010111 !
b10010111 .
1%
#25000
b11000 -
b10011 *
b1100 #
b1100 ,
b10 "
b10 +
0%
#25500
b10101111 !
b10101111 .
b10101111 '
1%
#26000
b111000 -
b10100 *
b111 #
b111 ,
b1000 "
b1000 +
0%
#26500
b11100111 '
b11100111 !
b11100111 .
1%
#27000
b1100011 -
b10101 *
1$
b1001 #
b1001 ,
b1011 "
b1011 +
0%
#27500
b0 !
b0 .
b0 '
1%
#28000
b111 -
b10110 *
0$
b1 #
b1 ,
b111 "
b111 +
0%
#28500
b111 '
b111 !
b111 .
1%
#29000
b10000 -
b10111 *
b1000 #
b1000 ,
b10 "
b10 +
0%
#29500
b10111 !
b10111 .
b10111 '
1%
#30000
b11100 -
b11000 *
b1110 #
b1110 ,
0%
#30500
b110011 '
b110011 !
b110011 .
1%
#31000
b101101 -
b11001 *
b11 #
b11 ,
b1111 "
b1111 +
0%
#31500
b1100000 !
b1100000 .
b1100000 '
1%
#32000
b1100011 -
b11010 *
b1001 #
b1001 ,
b1011 "
b1011 +
0%
#32500
b11000011 '
b11000011 !
b11000011 .
1%
#33000
b110000 -
b11011 *
b110 #
b110 ,
b1000 "
b1000 +
0%
#33500
b11110011 !
b11110011 .
b11110011 '
1%
#34000
b111100 -
b11100 *
b1010 "
b1010 +
0%
#34500
b101111 '
b101111 !
b101111 .
1%
#35000
b101101 -
b11101 *
b11 #
b11 ,
b1111 "
b1111 +
0%
#35500
b1011100 !
b1011100 .
b1011100 '
1%
#36000
b1001101 -
b11110 *
b1011 #
b1011 ,
b111 "
b111 +
0%
#36500
b10101001 '
b10101001 !
b10101001 .
1%
#37000
b1110101 -
b11111 *
b1101 #
b1101 ,
b1001 "
b1001 +
0%
#37500
b11110 !
b11110 .
b11110 '
1%
#38000
b1001011 -
b100000 *
b1111 #
b1111 ,
b101 "
b101 +
0%
#38500
b1101001 '
b1101001 !
b1101001 .
1%
#39000
b0 -
b100001 *
b1010 #
b1010 ,
b0 "
b0 +
0%
#39500
1%
#40000
b1111000 -
b100010 *
b1100 "
b1100 +
0%
#40500
b11100001 '
b11100001 !
b11100001 .
1%
#41000
b1010100 -
b100011 *
b1110 #
b1110 ,
b110 "
b110 +
0%
#41500
b110101 !
b110101 .
b110101 '
1%
#42000
b110000 -
b100100 *
b1000 #
b1000 ,
0%
#42500
b1100101 '
b1100101 !
b1100101 .
1%
#43000
b1100 -
b100101 *
0&
b11 #
b11 ,
b100 "
b100 +
0%
#43500
1%
#44000
b10001111 -
b100110 *
1&
b1101 #
b1101 ,
b1011 "
b1011 +
0%
#44500
b11110100 '
b11110100 !
b11110100 .
1%
#45000
b111100 -
b100111 *
b1010 #
b1010 ,
b110 "
b110 +
0%
#45500
b110000 !
b110000 .
b110000 '
1%
#46000
b11000 -
b101000 *
b100 #
b100 ,
0%
#46500
b1001000 '
b1001000 !
b1001000 .
1%
#47000
b100000 -
b101001 *
0&
b1000 #
b1000 ,
b100 "
b100 +
0%
#47500
1%
#48000
b1100010 -
b101010 *
b1110 #
b1110 ,
b111 "
b111 +
0%
#48500
1%
#49000
b1110101 -
b101011 *
b1001 #
b1001 ,
b1101 "
b1101 +
0%
#49500
1%
#50000
b10000010 -
b101100 *
1$
1&
b1101 #
b1101 ,
b1010 "
b1010 +
0%
#50500
b0 '
b0 !
b0 .
1%
#51000
b11110 -
b101101 *
0$
b1010 #
b1010 ,
b11 "
b11 +
0%
#51500
b11110 !
b11110 .
b11110 '
1%
#52000
b110010 -
b101110 *
b101 "
b101 +
0%
#52500
b1010000 '
b1010000 !
b1010000 .
1%
#53000
b0 -
b101111 *
b0 #
b0 ,
b110 "
b110 +
0%
#53500
1%
#54000
b10011100 -
b110000 *
b1100 #
b1100 ,
b1101 "
b1101 +
0%
#54500
b11101100 '
b11101100 !
b11101100 .
1%
#55000
b10011010 -
b110001 *
b1011 #
b1011 ,
b1110 "
b1110 +
0%
#55500
b10000110 !
b10000110 .
b10000110 '
1%
#56000
b1010 -
b110010 *
b1 #
b1 ,
b1010 "
b1010 +
0%
#56500
b10010000 '
b10010000 !
b10010000 .
1%
#57000
b0 -
b110011 *
b0 #
b0 ,
b110 "
b110 +
0%
#57500
1%
#58000
b1001 -
b110100 *
b1 #
b1 ,
b1001 "
b1001 +
0%
#58500
b10011001 '
b10011001 !
b10011001 .
1%
#59000
b100001 -
b110101 *
0&
b11 #
b11 ,
b1011 "
b1011 +
0%
#59500
1%
#60000
b1110000 -
b110110 *
1&
b1000 #
b1000 ,
b1110 "
b1110 +
0%
#60500
b1001 '
b1001 !
b1001 .
1%
#61000
b1010100 -
b110111 *
b110 #
b110 ,
0%
#61500
b1011101 !
b1011101 .
b1011101 '
1%
#62000
b10000010 -
b111000 *
b1101 #
b1101 ,
b1010 "
b1010 +
0%
#62500
b11011111 '
b11011111 !
b11011111 .
1%
#63000
b1001000 -
b111001 *
b1000 #
b1000 ,
b1001 "
b1001 +
0%
#63500
b100111 !
b100111 .
b100111 '
1%
#64000
b1001101 -
b111010 *
b111 #
b111 ,
b1011 "
b1011 +
0%
#64500
b1110100 '
b1110100 !
b1110100 .
1%
#65000
b100100 -
b111011 *
b1001 #
b1001 ,
b100 "
b100 +
0%
#65500
b10011000 !
b10011000 .
b10011000 '
1%
#66000
b1011010 -
b111100 *
b110 #
b110 ,
b1111 "
b1111 +
0%
#66500
b11110010 '
b11110010 !
b11110010 .
1%
#67000
b11010 -
b111101 *
0&
b1101 #
b1101 ,
b10 "
b10 +
0%
#67500
1%
#68000
b1011010 -
b111110 *
1&
b1001 #
b1001 ,
b1010 "
b1010 +
0%
#68500
b1001100 '
b1001100 !
b1001100 .
1%
#69000
b1111001 -
b111111 *
b1011 #
b1011 ,
b1011 "
b1011 +
0%
#69500
b11000101 !
b11000101 .
b11000101 '
1%
#70000
b11110 -
b1000000 *
b101 #
b101 ,
b110 "
b110 +
0%
#70500
b11100011 '
b11100011 !
b11100011 .
1%
#71000
b1110000 -
b1000001 *
b1110 #
b1110 ,
b1000 "
b1000 +
0%
#71500
b1010011 !
b1010011 .
b1010011 '
1%
#72000
b1101000 -
b1000010 *
b1101 #
b1101 ,
0%
#72500
b10111011 '
b10111011 !
b10111011 .
1%
#73000
b10110110 -
b1000011 *
0&
b1110 "
b1110 +
0%
#73500
1%
#74000
b110 -
b1000100 *
1&
b110 #
b110 ,
b1 "
b1 +
0%
#74500
b11000001 '
b11000001 !
b11000001 .
1%
#75000
b11000 -
b1000101 *
b11 #
b11 ,
b1000 "
b1000 +
0%
#75500
b11011001 !
b11011001 .
b11011001 '
1%
#76000
b1000 -
b1000110 *
b100 #
b100 ,
b10 "
b10 +
0%
#76500
b11100001 '
b11100001 !
b11100001 .
1%
#77000
b10000 -
b1000111 *
b1000 #
b1000 ,
0%
#77500
b11110001 !
b11110001 .
b11110001 '
1%
#78000
b1011 -
b1001000 *
b1011 #
b1011 ,
b1 "
b1 +
0%
#78500
b11111100 '
b11111100 !
b11111100 .
1%
#79000
b111 -
b1001001 *
b1 #
b1 ,
b111 "
b111 +
0%
#79500
b11 !
b11 .
b11 '
1%
#80000
b110000 -
b1001010 *
0&
b110 #
b110 ,
b1000 "
b1000 +
0%
#80500
1%
#81000
b110 -
b1001011 *
1&
b1 #
b1 ,
b110 "
b110 +
0%
#81500
b1001 !
b1001 .
b1001 '
1%
#82000
b110111 -
b1001100 *
b101 #
b101 ,
b1011 "
b1011 +
0%
#82500
b1000000 '
b1000000 !
b1000000 .
1%
#83000
b11100 -
b1001101 *
b111 #
b111 ,
b100 "
b100 +
0%
#83500
b1011100 !
b1011100 .
b1011100 '
1%
#84000
b1100011 -
b1001110 *
b1011 #
b1011 ,
b1001 "
b1001 +
0%
#84500
b10111111 '
b10111111 !
b10111111 .
1%
#85000
b1010 -
b1001111 *
b1010 #
b1010 ,
b1 "
b1 +
0%
#85500
b11001001 !
b11001001 .
b11001001 '
1%
#86000
b100100 -
b1010000 *
b1100 #
b1100 ,
b11 "
b11 +
0%
#86500
b11101101 '
b11101101 !
b11101101 .
1%
#87000
b1111000 -
b1010001 *
1$
b1111 #
b1111 ,
b1000 "
b1000 +
0%
#87500
b0 !
b0 .
b0 '
1%
#88000
b0 -
b1010010 *
0$
0&
b0 #
b0 ,
0%
#88500
1%
#89000
b1010011 *
b101 "
b101 +
0%
#89500
1%
#90000
b1010100 *
1&
b1100 #
b1100 ,
b0 "
b0 +
0%
#90500
1%
#91000
b101 -
b1010101 *
b1 #
b1 ,
b101 "
b101 +
0%
#91500
b101 !
b101 .
b101 '
1%
#92000
b110110 -
b1010110 *
b110 #
b110 ,
b1001 "
b1001 +
0%
#92500
b111011 '
b111011 !
b111011 .
1%
#93000
b10000010 -
b1010111 *
b1010 #
b1010 ,
b1101 "
b1101 +
0%
#93500
b10111101 !
b10111101 .
b10111101 '
1%
#94000
b1100 -
b1011000 *
b1 #
b1 ,
b1100 "
b1100 +
0%
#94500
b11001001 '
b11001001 !
b11001001 .
1%
#95000
b1100010 -
b1011001 *
0&
b1110 #
b1110 ,
b111 "
b111 +
0%
#95500
1%
#96000
b0 -
b1011010 *
1&
b0 #
b0 ,
b0 "
b0 +
0%
#96500
1%
#97000
b10101001 -
b1011011 *
b1101 #
b1101 ,
b1101 "
b1101 +
0%
#97500
b1110010 !
b1110010 .
b1110010 '
1%
#98000
b10110110 -
b1011100 *
b1110 "
b1110 +
0%
#98500
b101000 '
b101000 !
b101000 .
1%
#99000
b1001 -
b1011101 *
b11 #
b11 ,
b11 "
b11 +
0%
#99500
b110001 !
b110001 .
b110001 '
1%
#100000
b10100 -
b1011110 *
0&
b101 #
b101 ,
b100 "
b100 +
0%
#100500
1%
#101000
b10000 -
b1011111 *
1&
b1000 #
b1000 ,
b10 "
b10 +
0%
#101500
b1000001 !
b1000001 .
b1000001 '
1%
#102000
b11000 -
b1100000 *
1$
0&
b110 #
b110 ,
b100 "
b100 +
0%
#102500
b0 '
b0 !
b0 .
1%
#103000
b1000110 -
b1100001 *
0$
b1010 #
b1010 ,
b111 "
b111 +
0%
#103500
1%
#104000
b0 -
b1100010 *
1&
b0 #
b0 ,
b1100 "
b1100 +
0%
#104500
1%
#105000
b11110 -
b1100011 *
b101 #
b101 ,
b110 "
b110 +
0%
#105500
b11110 !
b11110 .
b11110 '
1%
#106000
b100100 -
b1100100 *
b100 #
b100 ,
b1001 "
b1001 +
0%
#106500
b1000010 '
b1000010 !
b1000010 .
1%
#107000
b1010100 -
b1100101 *
b111 #
b111 ,
b1100 "
b1100 +
0%
#107500
b10010110 !
b10010110 .
b10010110 '
1%
#108000
b0 -
b1100110 *
0&
b0 #
b0 ,
b100 "
b100 +
0%
#108500
1%
#109000
b1000110 -
b1100111 *
1&
b1010 #
b1010 ,
b111 "
b111 +
0%
#109500
b11011100 !
b11011100 .
b11011100 '
1%
#110000
b100001 -
b1101000 *
0&
b11 #
b11 ,
b1011 "
b1011 +
0%
#110500
1%
#111000
b100100 -
b1101001 *
1&
b1001 #
b1001 ,
b100 "
b100 +
0%
#111500
b0 !
b0 .
b0 '
1%
#112000
b11100 -
b1101010 *
1$
b111 #
b111 ,
0%
#112500
1%
#113000
b10010 -
b1101011 *
b1001 #
b1001 ,
b10 "
b10 +
0%
#113500
1%
#114000
b100100 -
b1101100 *
0$
b11 #
b11 ,
b1100 "
b1100 +
0%
#114500
b100100 '
b100100 !
b100100 .
1%
#115000
b1101000 -
b1101101 *
b1101 #
b1101 ,
b1000 "
b1000 +
0%
#115500
b10001100 !
b10001100 .
b10001100 '
1%
#116000
b1100011 -
b1101110 *
b1001 #
b1001 ,
b1011 "
b1011 +
0%
#116500
b11101111 '
b11101111 !
b11101111 .
1%
#117000
b0 -
b1101111 *
b0 #
b0 ,
b1001 "
b1001 +
0%
#117500
1%
#118000
b1000010 -
b1110000 *
1$
b110 #
b110 ,
b1011 "
b1011 +
0%
#118500
b0 '
b0 !
b0 .
1%
#119000
b10000111 -
b1110001 *
0$
0&
b1001 #
b1001 ,
b1111 "
b1111 +
0%
#119500
1%
#120000
b1001011 -
b1110010 *
b1111 #
b1111 ,
b101 "
b101 +
0%
#120500
1%
#121000
b111111 -
b1110011 *
1&
b111 #
b111 ,
b1001 "
b1001 +
0%
#121500
b111111 !
b111111 .
b111111 '
1%
#122000
b101100 -
b1110100 *
0&
b100 #
b100 ,
b1011 "
b1011 +
0%
#122500
1%
#123000
b0 -
b1110101 *
1&
b0 #
b0 ,
b110 "
b110 +
0%
#123500
1%
#124000
b11100 -
b1110110 *
b111 #
b111 ,
b100 "
b100 +
0%
#124500
b1011011 '
b1011011 !
b1011011 .
1%
#125000
b1011 -
b1110111 *
1$
b1 #
b1 ,
b1011 "
b1011 +
0%
#125500
b0 !
b0 .
b0 '
1%
#126000
b1010 -
b1111000 *
0$
0&
b101 #
b101 ,
b10 "
b10 +
0%
#126500
1%
#127000
b1011010 -
b1111001 *
1&
b1111 #
b1111 ,
b110 "
b110 +
0%
#127500
b1011010 !
b1011010 .
b1011010 '
1%
#128000
b1111010 *
0%
#128500
b10110100 '
b10110100 !
b10110100 .
1%
#129000
b0 -
b1111011 *
b0 #
b0 ,
b1110 "
b1110 +
0%
#129500
1%
#130000
b100100 -
b1111100 *
b1001 #
b1001 ,
b100 "
b100 +
0%
#130500
b11011000 '
b11011000 !
b11011000 .
1%
#131000
b1110 -
b1111101 *
b1 #
b1 ,
b1110 "
b1110 +
0%
#131500
b11100110 !
b11100110 .
b11100110 '
1%
#132000
b0 -
b1111110 *
b1010 #
b1010 ,
b0 "
b0 +
0%
#132500
1%
#133000
b10110110 -
b1111111 *
b1110 #
b1110 ,
b1101 "
b1101 +
0%
#133500
b10011100 !
b10011100 .
b10011100 '
1%
#134000
b10000111 -
b10000000 *
b1111 #
b1111 ,
b1001 "
b1001 +
0%
#134500
b100011 '
b100011 !
b100011 .
1%
#135000
b1011010 -
b10000001 *
b1001 #
b1001 ,
b1010 "
b1010 +
0%
#135500
b1111101 !
b1111101 .
b1111101 '
1%
#136000
b101 -
b10000010 *
b1 #
b1 ,
b101 "
b101 +
0%
#136500
b10000010 '
b10000010 !
b10000010 .
1%
#137000
b1010 -
b10000011 *
b1010 "
b1010 +
0%
#137500
b10001100 !
b10001100 .
b10001100 '
1%
#138000
b10000010 -
b10000100 *
b1101 #
b1101 ,
0%
#138500
b1110 '
b1110 !
b1110 .
1%
#139000
b1110101 -
b10000101 *
b1001 #
b1001 ,
b1101 "
b1101 +
0%
#139500
b10000011 !
b10000011 .
b10000011 '
1%
#140000
b10001111 -
b10000110 *
0&
b1101 #
b1101 ,
b1011 "
b1011 +
0%
#140500
1%
#141000
b11010 -
b10000111 *
1&
b10 "
b10 +
0%
#141500
b10011101 !
b10011101 .
b10011101 '
1%
#142000
b0 -
b10001000 *
b1011 #
b1011 ,
b0 "
b0 +
0%
#142500
1%
#143000
b1001000 -
b10001001 *
b1100 #
b1100 ,
b110 "
b110 +
0%
#143500
b11100101 !
b11100101 .
b11100101 '
1%
#144000
b1011000 -
b10001010 *
b1011 #
b1011 ,
b1000 "
b1000 +
0%
#144500
b111101 '
b111101 !
b111101 .
1%
#145000
b10101000 -
b10001011 *
0&
b1110 #
b1110 ,
b1100 "
b1100 +
0%
#145500
1%
#146000
b11011 -
b10001100 *
b11 #
b11 ,
b1001 "
b1001 +
0%
#146500
1%
#147000
b1101100 -
b10001101 *
1&
b1001 #
b1001 ,
b1100 "
b1100 +
0%
#147500
b10101001 !
b10101001 .
b10101001 '
1%
#148000
b1000110 -
b10001110 *
b1110 #
b1110 ,
b101 "
b101 +
0%
#148500
b11101111 '
b11101111 !
b11101111 .
1%
#149000
b1101000 -
b10001111 *
b1101 #
b1101 ,
b1000 "
b1000 +
0%
#149500
b1010111 !
b1010111 .
b1010111 '
1%
#150000
b0 -
b10010000 *
0&
b101 #
b101 ,
b0 "
b0 +
0%
#150500
1%
#151000
b10010001 *
1$
1&
0%
#151500
b0 !
b0 .
b0 '
1%
#152000
b1110101 -
b10010010 *
0&
b1001 #
b1001 ,
b1101 "
b1101 +
0%
#152500
1%
#153000
b0 -
b10010011 *
0$
1&
b0 #
b0 ,
b0 "
b0 +
0%
#153500
1%
#154000
b11001 -
b10010100 *
b101 #
b101 ,
b101 "
b101 +
0%
#154500
b11001 '
b11001 !
b11001 .
1%
#155000
b1111000 -
b10010101 *
0&
b1100 #
b1100 ,
b1010 "
b1010 +
0%
#155500
1%
#156000
b111100 -
b10010110 *
1&
b110 #
b110 ,
0%
#156500
b1010101 '
b1010101 !
b1010101 .
1%
#157000
b100011 -
b10010111 *
b111 #
b111 ,
b101 "
b101 +
0%
#157500
b1111000 !
b1111000 .
b1111000 '
1%
#158000
b110110 -
b10011000 *
0&
b110 #
b110 ,
b1001 "
b1001 +
0%
#158500
1%
#159000
b0 -
b10011001 *
b1010 #
b1010 ,
b0 "
b0 +
0%
#159500
1%
#160000
b0 -
b10011010 *
1&
b0 #
b0 ,
b1011 "
b1011 +
0%
#160500
1%
#161000
b1000001 -
b10011011 *
b1101 #
b1101 ,
b101 "
b101 +
0%
#161500
b10111001 !
b10111001 .
b10111001 '
1%
#162000
b110000 -
b10011100 *
b100 #
b100 ,
b1100 "
b1100 +
0%
#162500
b11101001 '
b11101001 !
b11101001 .
1%
#163000
b101010 -
b10011101 *
0&
b11 #
b11 ,
b1110 "
b1110 +
0%
#163500
1%
#164000
b1001000 -
b10011110 *
1&
b110 #
b110 ,
b1100 "
b1100 +
0%
#164500
b110001 '
b110001 !
b110001 .
1%
#165000
b110010 -
b10011111 *
b1010 #
b1010 ,
b101 "
b101 +
0%
#165500
b1100011 !
b1100011 .
b1100011 '
1%
#166000
b11000 -
b10100000 *
b1100 #
b1100 ,
b10 "
b10 +
0%
#166500
b1111011 '
b1111011 !
b1111011 .
1%
#167000
b1011000 -
b10100001 *
b1000 #
b1000 ,
b1011 "
b1011 +
0%
#167500
b11010011 !
b11010011 .
b11010011 '
1%
#168000
b10100101 -
b10100010 *
b1011 #
b1011 ,
b1111 "
b1111 +
0%
#168500
b1111000 '
b1111000 !
b1111000 .
1%
#169000
b1001011 -
b10100011 *
b1111 #
b1111 ,
b101 "
b101 +
0%
#169500
b11000011 !
b11000011 .
b11000011 '
1%
#170000
b0 -
b10100100 *
b1101 #
b1101 ,
b0 "
b0 +
0%
#170500
1%
#171000
b101010 -
b10100101 *
b110 #
b110 ,
b111 "
b111 +
0%
#171500
b11101101 !
b11101101 .
b11101101 '
1%
#172000
b11000 -
b10100110 *
1$
b100 "
b100 +
0%
#172500
b0 '
b0 !
b0 .
1%
#173000
b10101000 -
b10100111 *
0$
b1100 #
b1100 ,
b1110 "
b1110 +
0%
#173500
b10101000 !
b10101000 .
b10101000 '
1%
#174000
b10010000 -
b10101000 *
b1100 "
b1100 +
0%
#174500
b111000 '
b111000 !
b111000 .
1%
#175000
b110111 -
b10101001 *
b101 #
b101 ,
b1011 "
b1011 +
0%
#175500
b1101111 !
b1101111 .
b1101111 '
1%
#176000
b0 -
b10101010 *
b0 #
b0 ,
b1111 "
b1111 +
0%
#176500
1%
#177000
b10100 -
b10101011 *
b1010 #
b1010 ,
b10 "
b10 +
0%
#177500
b10000011 !
b10000011 .
b10000011 '
1%
#178000
b1110 -
b10101100 *
b1 #
b1 ,
b1110 "
b1110 +
0%
#178500
b10010001 '
b10010001 !
b10010001 .
1%
#179000
b1100000 -
b10101101 *
0&
b1000 #
b1000 ,
b1100 "
b1100 +
0%
#179500
1%
#180000
b100011 -
b10101110 *
1&
b111 #
b111 ,
b101 "
b101 +
0%
#180500
b10110100 '
b10110100 !
b10110100 .
1%
#181000
b10110110 -
b10101111 *
0&
b1110 #
b1110 ,
b1101 "
b1101 +
0%
#181500
1%
#182000
b0 -
b10110000 *
1&
b110 #
b110 ,
b0 "
b0 +
0%
#182500
1%
#183000
b1000110 -
b10110001 *
b1110 #
b1110 ,
b101 "
b101 +
0%
#183500
b11111010 !
b11111010 .
b11111010 '
1%
#184000
b1111001 -
b10110010 *
b1011 #
b1011 ,
b1011 "
b1011 +
0%
#184500
b1110011 '
b1110011 !
b1110011 .
1%
#185000
b101000 -
b10110011 *
b1010 #
b1010 ,
b100 "
b100 +
0%
#185500
b10011011 !
b10011011 .
b10011011 '
1%
#186000
b1111001 -
b10110100 *
0&
b1011 #
b1011 ,
b1011 "
b1011 +
0%
#186500
1%
#187000
b1101 -
b10110101 *
1&
b1 #
b1 ,
b1101 "
b1101 +
0%
#187500
b10101000 !
b10101000 .
b10101000 '
1%
#188000
b0 -
b10110110 *
b0 #
b0 ,
b1001 "
b1001 +
0%
#188500
1%
#189000
b111000 -
b10110111 *
b1000 #
b1000 ,
b111 "
b111 +
0%
#189500
b11100000 !
b11100000 .
b11100000 '
1%
#190000
b0 -
b10111000 *
1$
0&
b0 #
b0 ,
b1100 "
b1100 +
0%
#190500
b0 '
b0 !
b0 .
1%
#191000
b11000 -
b10111001 *
0$
1&
b1000 #
b1000 ,
b11 "
b11 +
0%
#191500
b11000 !
b11000 .
b11000 '
1%
#192000
b1111000 -
b10111010 *
b1111 #
b1111 ,
b1000 "
b1000 +
0%
#192500
b10010000 '
b10010000 !
b10010000 .
1%
#193000
b0 -
b10111011 *
b0 #
b0 ,
b1101 "
b1101 +
0%
#193500
1%
#194000
b11000 -
b10111100 *
b1100 #
b1100 ,
b10 "
b10 +
0%
#194500
b10101000 '
b10101000 !
b10101000 .
1%
#195000
b0 -
b10111101 *
1$
0&
b100 #
b100 ,
b0 "
b0 +
0%
#195500
b0 !
b0 .
b0 '
1%
#196000
b1001 -
b10111110 *
0$
1&
b11 #
b11 ,
b11 "
b11 +
0%
#196500
b1001 '
b1001 !
b1001 .
1%
#197000
b111000 -
b10111111 *
b111 #
b111 ,
b1000 "
b1000 +
0%
#197500
b1000001 !
b1000001 .
b1000001 '
1%
#198000
b1011000 -
b11000000 *
b1000 #
b1000 ,
b1011 "
b1011 +
0%
#198500
b10011001 '
b10011001 !
b10011001 .
1%
#199000
b1110 -
b11000001 *
b10 #
b10 ,
b111 "
b111 +
0%
#199500
b10100111 !
b10100111 .
b10100111 '
1%
#200000
b101100 -
b11000010 *
0&
b1011 #
b1011 ,
b100 "
b100 +
0%
#200500
1%
#201000
b110010 -
b11000011 *
b1010 #
b1010 ,
b101 "
b101 +
0%
#201500
1%
#202000
b0 -
b11000100 *
1&
b0 #
b0 ,
b1000 "
b1000 +
0%
#202500
1%
#203000
b110010 -
b11000101 *
b1010 #
b1010 ,
b101 "
b101 +
0%
#203500
b11011001 !
b11011001 .
b11011001 '
1%
#204000
b1011000 -
b11000110 *
0&
b1000 #
b1000 ,
b1011 "
b1011 +
0%
#204500
1%
#205000
b101000 -
b11000111 *
1&
b101 #
b101 ,
b1000 "
b1000 +
0%
#205500
b1 !
b1 .
b1 '
1%
#206000
b110111 -
b11001000 *
0&
b1011 "
b1011 +
0%
